MANIFEST.in
README.rst
dev_requirements.txt
flagen.py
requirements.txt
setup.py
flagen.egg-info/PKG-INFO
flagen.egg-info/SOURCES.txt
flagen.egg-info/dependency_links.txt
flagen.egg-info/entry_points.txt
flagen.egg-info/requires.txt
flagen.egg-info/top_level.txt